build/dut.v
// File: ./build/dut.v
// Generated by MyHDL 0.10
// Date: Tue Dec 11 13:00:12 2018


`timescale 1ns/10ps

module dut (
    clk_i,
    rst_i,
    rx_i,
    tx_o,
    anodos_o,
    segmentos_o
);


input clk_i;
input rst_i;
input rx_i;
output tx_o;
reg tx_o;
output [3:0] anodos_o;
reg [3:0] anodos_o;
output [7:0] segmentos_o;
reg [7:0] segmentos_o;

wire [10:0] value;
wire [7:0] dat;
reg tx_start;
reg tx_ready;
reg [0:0] state;
reg rx_ready;
wire [7:0] rx_dat;
wire full;
wire empty;
reg dequeue;
reg UART1_tx_tick;
reg UART1_rx_tick;
reg [3:0] UART1_clk_div1_counter8;
reg [2:0] UART1_clk_div1_counter;
reg [0:0] UART1_uart_tx1_state;
reg [7:0] UART1_uart_tx1_data;
reg [3:0] UART1_uart_tx1_cnt;
reg [1:0] UART1_uart_rx1_state;
reg [2:0] UART1_uart_rx1_rx_sync;
wire UART1_uart_rx1_rx_r;
reg UART1_uart_rx1_nxt_bit;
reg [7:0] UART1_uart_rx1_dat_r;
reg [1:0] UART1_uart_rx1_bit_start;
reg [2:0] UART1_uart_rx1_bit_spacing;
reg [2:0] UART1_uart_rx1_bit_cnt;
reg [7:0] FIFO1_ram_dat_o;
reg [9:0] FIFO1_enqueue_ptr;
reg [9:0] FIFO1_dequeue_ptr;
wire FIFO1__full;
wire FIFO1__enqueue;
wire FIFO1__empty;
wire FIFO1__dequeue;
reg [10:0] FIFO1__count;
reg driver7seg1_tick;
reg [3:0] driver7seg1_thousand;
reg [3:0] driver7seg1_ten;
reg [3:0] driver7seg1_one;
reg [3:0] driver7seg1_hundred;
reg [15:0] driver7seg1_counter;
reg [3:0] driver7seg1_anodos;
reg [7:0] FIFO1_RAM_DP1__ram [0:1024-1];
reg [26:0] driver7seg1_bin2bcd1_shift [0:12-1];



always @(posedge clk_i) begin: DUT_UART1_CLK_DIV1_COUNTER_PROC
    if (rst_i == 1) begin
        UART1_clk_div1_counter <= 0;
    end
    else begin
        if ((UART1_clk_div1_counter8 == 0)) begin
            UART1_clk_div1_counter <= (UART1_clk_div1_counter + 1);
        end
    end
end


always @(posedge clk_i) begin: DUT_UART1_CLK_DIV1_COUNTER16_PROC
    if (rst_i == 1) begin
        UART1_clk_div1_counter8 <= 0;
    end
    else begin
        if (($signed({1'b0, UART1_clk_div1_counter8}) == (13 - 1))) begin
            UART1_clk_div1_counter8 <= 0;
        end
        else begin
            UART1_clk_div1_counter8 <= (UART1_clk_div1_counter8 + 1);
        end
    end
end


always @(posedge clk_i) begin: DUT_UART1_CLK_DIV1_UART_TICK_PROC
    if (rst_i == 1) begin
        UART1_tx_tick <= 0;
        UART1_rx_tick <= 0;
    end
    else begin
        UART1_rx_tick <= (UART1_clk_div1_counter8 == 0);
        UART1_tx_tick <= ((UART1_clk_div1_counter == 0) && UART1_rx_tick);
    end
end


always @(posedge clk_i) begin: DUT_UART1_UART_TX1_TX_STATE_M
    if (rst_i == 1) begin
        UART1_uart_tx1_state <= 1'b0;
        UART1_uart_tx1_data <= 0;
        tx_ready <= 0;
        UART1_uart_tx1_cnt <= 0;
        tx_o <= 0;
    end
    else begin
        case (UART1_uart_tx1_state)
            1'b0: begin
                tx_ready <= 1;
                if (tx_start) begin
                    UART1_uart_tx1_data <= dat;
                    tx_ready <= 0;
                    UART1_uart_tx1_state <= 1'b1;
                end
                else begin
                    tx_o <= 1;
                end
            end
            1'b1: begin
                if (UART1_tx_tick) begin
                    if (((UART1_uart_tx1_cnt >= 1) && (UART1_uart_tx1_cnt <= 8))) begin
                        tx_o <= UART1_uart_tx1_data[0];
                        UART1_uart_tx1_data <= {1'b0, UART1_uart_tx1_data[8-1:1]};
                        UART1_uart_tx1_cnt <= (UART1_uart_tx1_cnt + 1);
                    end
                    else begin
                        tx_o <= 0;
                        UART1_uart_tx1_cnt <= (UART1_uart_tx1_cnt + 1);
                    end
                    if ((UART1_uart_tx1_cnt == 9)) begin
                        tx_o <= 1;
                        tx_ready <= 1;
                        UART1_uart_tx1_state <= 1'b0;
                        UART1_uart_tx1_cnt <= 0;
                    end
                end
            end
            default: begin
                UART1_uart_tx1_state <= 1'b0;
            end
        endcase
    end
end


always @(posedge clk_i) begin: DUT_UART1_UART_RX1_RX_SYNC_PROC
    if (rst_i == 1) begin
        UART1_uart_rx1_rx_sync <= 7;
    end
    else begin
        if (UART1_rx_tick) begin
            UART1_uart_rx1_rx_sync <= {UART1_uart_rx1_rx_sync[2-1:0], rx_i};
        end
    end
end



assign UART1_uart_rx1_rx_r = ((UART1_uart_rx1_rx_sync == 7) || (UART1_uart_rx1_rx_sync == 3) || (UART1_uart_rx1_rx_sync == 5) || (UART1_uart_rx1_rx_sync == 6));
assign rx_dat = UART1_uart_rx1_dat_r;


always @(posedge clk_i) begin: DUT_UART1_UART_RX1_NXT_BIT_PROC
    if (rst_i == 1) begin
        UART1_uart_rx1_bit_spacing <= 0;
        UART1_uart_rx1_nxt_bit <= 0;
    end
    else begin
        UART1_uart_rx1_nxt_bit <= ($signed({1'b0, UART1_uart_rx1_bit_spacing}) == (8 - 1));
        if ((UART1_rx_tick && (UART1_uart_rx1_state != 2'b00))) begin
            UART1_uart_rx1_bit_spacing <= (UART1_uart_rx1_bit_spacing + 1);
        end
    end
end


always @(posedge clk_i) begin: DUT_UART1_UART_RX1_START_BIT_PROC
    if (rst_i == 1) begin
        UART1_uart_rx1_bit_start <= 0;
    end
    else begin
        if (((UART1_uart_rx1_state == 2'b00) && (!UART1_uart_rx1_rx_r))) begin
            UART1_uart_rx1_bit_start <= (UART1_uart_rx1_bit_start + UART1_rx_tick);
        end
        else begin
            UART1_uart_rx1_bit_start <= 0;
        end
    end
end


always @(posedge clk_i) begin: DUT_UART1_UART_RX1_FSM_PROC
    if (rst_i == 1) begin
        rx_ready <= 0;
        UART1_uart_rx1_bit_cnt <= 0;
        UART1_uart_rx1_state <= 2'b00;
        UART1_uart_rx1_dat_r <= 0;
    end
    else begin
        rx_ready <= 1'b0;
        if (UART1_rx_tick) begin
            case (UART1_uart_rx1_state)
                2'b00: begin
                    if (((!UART1_uart_rx1_rx_r) && (UART1_uart_rx1_bit_start == 2'h3))) begin
                        UART1_uart_rx1_state <= 2'b01;
                    end
                end
                2'b01: begin
                    if (UART1_uart_rx1_nxt_bit) begin
                        UART1_uart_rx1_dat_r <= {UART1_uart_rx1_rx_r, UART1_uart_rx1_dat_r[8-1:1]};
                        UART1_uart_rx1_bit_cnt <= (UART1_uart_rx1_bit_cnt + 1);
                        if ((UART1_uart_rx1_bit_cnt == 7)) begin
                            UART1_uart_rx1_state <= 2'b10;
                        end
                    end
                end
                2'b10: begin
                    if (UART1_uart_rx1_nxt_bit) begin
                        UART1_uart_rx1_state <= 2'b00;
                        rx_ready <= 1'b1;
                    end
                end
                default: begin
                    UART1_uart_rx1_state <= 2'b00;
                end
            endcase
        end
    end
end


always @(posedge clk_i) begin: DUT_FIFO1_RAM_DP1_RAM_PROC
    if (FIFO1__enqueue) begin
        FIFO1_RAM_DP1__ram[FIFO1_enqueue_ptr] <= rx_dat;
    end
    FIFO1_ram_dat_o <= FIFO1_RAM_DP1__ram[FIFO1_dequeue_ptr];
end



assign value = FIFO1__count;
assign empty = FIFO1__empty;
assign full = FIFO1__full;
assign dat = FIFO1__empty ? rx_dat : FIFO1_ram_dat_o;



assign FIFO1__empty = (FIFO1__count == 0);
assign FIFO1__full = FIFO1__count[10];



assign FIFO1__enqueue = ((!FIFO1__full) && rx_ready);
assign FIFO1__dequeue = ((!FIFO1__empty) && dequeue);

// verilator lint_off WIDTH 
always @(posedge clk_i) begin: DUT_FIFO1_ADDR_PTR_PROC
    if (rst_i == 1) begin
        FIFO1_enqueue_ptr <= 0;
        FIFO1__count <= 0;
        FIFO1_dequeue_ptr <= 0;
    end
    else begin
        FIFO1_enqueue_ptr <= (FIFO1_enqueue_ptr + FIFO1__enqueue);
        FIFO1_dequeue_ptr <= (FIFO1_dequeue_ptr + FIFO1__dequeue);
        FIFO1__count <= ((FIFO1__count + FIFO1__enqueue) - FIFO1__dequeue);
        // verilator lint_on WIDTH 
    end
end

// verilator lint_off WIDTH 
always @(posedge clk_i) begin: DUT_DRIVER7SEG1_BIN2BCD1_DECOMP_PROC
    integer i;
    integer thousand;
    integer hundred;
    integer ten;
    integer one;
    if (rst_i == 1) begin
        driver7seg1_bin2bcd1_shift[0] <= 0;
        driver7seg1_bin2bcd1_shift[1] <= 0;
        driver7seg1_bin2bcd1_shift[2] <= 0;
        driver7seg1_bin2bcd1_shift[3] <= 0;
        driver7seg1_bin2bcd1_shift[4] <= 0;
        driver7seg1_bin2bcd1_shift[5] <= 0;
        driver7seg1_bin2bcd1_shift[6] <= 0;
        driver7seg1_bin2bcd1_shift[7] <= 0;
        driver7seg1_bin2bcd1_shift[8] <= 0;
        driver7seg1_bin2bcd1_shift[9] <= 0;
        driver7seg1_bin2bcd1_shift[10] <= 0;
        driver7seg1_bin2bcd1_shift[11] <= 0;
    end
    else begin
        driver7seg1_bin2bcd1_shift[0] <= value;
        for (i=0; i<11; i=i+1) begin
            thousand = (driver7seg1_bin2bcd1_shift[i][(11 + 16)-1:(11 + 12)] + 3);
            hundred = (driver7seg1_bin2bcd1_shift[i][(11 + 12)-1:(11 + 8)] + 3);
            ten = (driver7seg1_bin2bcd1_shift[i][(11 + 8)-1:(11 + 4)] + 3);
            one = (driver7seg1_bin2bcd1_shift[i][(11 + 4)-1:11] + 3);
            driver7seg1_bin2bcd1_shift[(i + 1)] <= ({(driver7seg1_bin2bcd1_shift[i][(11 + 16)-1:(11 + 12)] < 5) ? driver7seg1_bin2bcd1_shift[i][(11 + 16)-1:(11 + 12)] : thousand[4-1:0], (driver7seg1_bin2bcd1_shift[i][(11 + 12)-1:(11 + 8)] < 5) ? driver7seg1_bin2bcd1_shift[i][(11 + 12)-1:(11 + 8)] : hundred[4-1:0], (driver7seg1_bin2bcd1_shift[i][(11 + 8)-1:(11 + 4)] < 5) ? driver7seg1_bin2bcd1_shift[i][(11 + 8)-1:(11 + 4)] : ten[4-1:0], (driver7seg1_bin2bcd1_shift[i][(11 + 4)-1:11] < 5) ? driver7seg1_bin2bcd1_shift[i][(11 + 4)-1:11] : one[4-1:0], driver7seg1_bin2bcd1_shift[i][11-1:0]} << 1);
        end
        // verilator lint_on WIDTH 
    end
end


always @(posedge clk_i) begin: DUT_DRIVER7SEG1_BIN2BCD1_ASSIGN_PROC
    if (rst_i == 1) begin
        driver7seg1_hundred <= 0;
        driver7seg1_thousand <= 0;
        driver7seg1_one <= 0;
        driver7seg1_ten <= 0;
    end
    else begin
        driver7seg1_thousand <= driver7seg1_bin2bcd1_shift[11][(11 + 16)-1:(11 + 12)];
        driver7seg1_hundred <= driver7seg1_bin2bcd1_shift[11][(11 + 12)-1:(11 + 8)];
        driver7seg1_ten <= driver7seg1_bin2bcd1_shift[11][(11 + 8)-1:(11 + 4)];
        driver7seg1_one <= driver7seg1_bin2bcd1_shift[11][(11 + 4)-1:11];
    end
end


always @(posedge clk_i) begin: DUT_DRIVER7SEG1_CNT_ANODOS_PROC
    if (rst_i == 1) begin
        driver7seg1_tick <= 0;
        driver7seg1_counter <= 0;
    end
    else begin
        if (($signed({1'b0, driver7seg1_counter}) == (50000 - 1))) begin
            driver7seg1_counter <= 0;
            driver7seg1_tick <= 1'b1;
        end
        else begin
            driver7seg1_counter <= (driver7seg1_counter + 1);
            driver7seg1_tick <= 1'b0;
        end
    end
end


always @(posedge clk_i) begin: DUT_DRIVER7SEG1_ANODOS_PROC
    if (rst_i == 1) begin
        driver7seg1_anodos <= 1;
    end
    else begin
        if (driver7seg1_tick) begin
            driver7seg1_anodos <= {driver7seg1_anodos[3-1:0], driver7seg1_anodos[3]};
        end
    end
end


always @(driver7seg1_ten, driver7seg1_one, driver7seg1_anodos, driver7seg1_hundred, driver7seg1_thousand) begin: DUT_DRIVER7SEG1_SEGMENTOS_PROC
    anodos_o = driver7seg1_anodos;
    case (driver7seg1_anodos)
        'h1: begin
            case (driver7seg1_one)
                0: segmentos_o = 3;
                1: segmentos_o = 159;
                2: segmentos_o = 37;
                3: segmentos_o = 13;
                4: segmentos_o = 153;
                5: segmentos_o = 73;
                6: segmentos_o = 65;
                7: segmentos_o = 31;
                8: segmentos_o = 1;
                9: segmentos_o = 9;
                10: segmentos_o = 17;
                11: segmentos_o = 193;
                12: segmentos_o = 99;
                13: segmentos_o = 133;
                14: segmentos_o = 97;
                default: segmentos_o = 113;
            endcase
        end
        'h2: begin
            case (driver7seg1_ten)
                0: segmentos_o = 3;
                1: segmentos_o = 159;
                2: segmentos_o = 37;
                3: segmentos_o = 13;
                4: segmentos_o = 153;
                5: segmentos_o = 73;
                6: segmentos_o = 65;
                7: segmentos_o = 31;
                8: segmentos_o = 1;
                9: segmentos_o = 9;
                10: segmentos_o = 17;
                11: segmentos_o = 193;
                12: segmentos_o = 99;
                13: segmentos_o = 133;
                14: segmentos_o = 97;
                default: segmentos_o = 113;
            endcase
        end
        'h4: begin
            case (driver7seg1_hundred)
                0: segmentos_o = 3;
                1: segmentos_o = 159;
                2: segmentos_o = 37;
                3: segmentos_o = 13;
                4: segmentos_o = 153;
                5: segmentos_o = 73;
                6: segmentos_o = 65;
                7: segmentos_o = 31;
                8: segmentos_o = 1;
                9: segmentos_o = 9;
                10: segmentos_o = 17;
                11: segmentos_o = 193;
                12: segmentos_o = 99;
                13: segmentos_o = 133;
                14: segmentos_o = 97;
                default: segmentos_o = 113;
            endcase
        end
        'h8: begin
            case (driver7seg1_thousand)
                0: segmentos_o = 3;
                1: segmentos_o = 159;
                2: segmentos_o = 37;
                3: segmentos_o = 13;
                4: segmentos_o = 153;
                5: segmentos_o = 73;
                6: segmentos_o = 65;
                7: segmentos_o = 31;
                8: segmentos_o = 1;
                9: segmentos_o = 9;
                10: segmentos_o = 17;
                11: segmentos_o = 193;
                12: segmentos_o = 99;
                13: segmentos_o = 133;
                14: segmentos_o = 97;
                default: segmentos_o = 113;
            endcase
        end
        default: begin
            segmentos_o = 255;
        end
    endcase
end


always @(posedge clk_i) begin: DUT_L_STATE_M
    if (rst_i == 1) begin
        dequeue <= 0;
        tx_start <= 0;
        state <= 1'b0;
    end
    else begin
        case (state)
            1'b0: begin
                if (rx_ready) begin
                    if (((rx_dat == 10) || full)) begin
                        state <= 1'b1;
                    end
                end
            end
            1'b1: begin
                if ((!empty)) begin
                    dequeue <= 0;
                    tx_start <= 0;
                end
                if (empty) begin
                    state <= 1'b0;
                end
                else if ((tx_ready && (!dequeue))) begin
                    dequeue <= 1;
                    tx_start <= 1;
                end
            end
            default: begin
                state <= 1'b1;
            end
        endcase
    end
end

endmodule

build/tb_dut.v
module tb_dut;

reg clk_i;
reg rst_i;
reg rx_i;
wire tx_o;
wire [3:0] anodos_o;
wire [7:0] segmentos_o;

initial begin
    $dumpfile("dut.vcd");
    $dumpvars(0, dut);
    $from_myhdl(
        clk_i,
        rst_i,
        rx_i
    );
    $to_myhdl(
        tx_o,
        anodos_o,
        segmentos_o
    );
end

dut dut(
    clk_i,
    rst_i,
    rx_i,
    tx_o,
    anodos_o,
    segmentos_o
);

endmodule

dut.vcd
$date
	Tue Dec 11 13:00:12 2018
$end
$version
	Icarus Verilog
$end
$timescale
	10ps
$end
$scope module tb_dut $end
$scope module dut $end
$var wire 1 ! FIFO1__dequeue $end
$var wire 1 " FIFO1__enqueue $end
$var wire 1 # UART1_uart_rx1_rx_r $end
$var wire 1 $ clk_i $end
$var wire 1 % empty $end
$var wire 1 & full $end
$var wire 1 ' rst_i $end
$var wire 8 ( rx_dat [7:0] $end
$var wire 1 ) rx_i $end
$var wire 11 * value [10:0] $end
$var wire 8 + dat [7:0] $end
$var wire 1 , FIFO1__full $end
$var wire 1 - FIFO1__empty $end
$var reg 11 . FIFO1__count [10:0] $end
$var reg 10 / FIFO1_dequeue_ptr [9:0] $end
$var reg 10 0 FIFO1_enqueue_ptr [9:0] $end
$var reg 8 1 FIFO1_ram_dat_o [7:0] $end
$var reg 3 2 UART1_clk_div1_counter [2:0] $end
$var reg 4 3 UART1_clk_div1_counter8 [3:0] $end
$var reg 1 4 UART1_rx_tick $end
$var reg 1 5 UART1_tx_tick $end
$var reg 3 6 UART1_uart_rx1_bit_cnt [2:0] $end
$var reg 3 7 UART1_uart_rx1_bit_spacing [2:0] $end
$var reg 2 8 UART1_uart_rx1_bit_start [1:0] $end
$var reg 8 9 UART1_uart_rx1_dat_r [7:0] $end
$var reg 1 : UART1_uart_rx1_nxt_bit $end
$var reg 3 ; UART1_uart_rx1_rx_sync [2:0] $end
$var reg 2 < UART1_uart_rx1_state [1:0] $end
$var reg 4 = UART1_uart_tx1_cnt [3:0] $end
$var reg 8 > UART1_uart_tx1_data [7:0] $end
$var reg 1 ? UART1_uart_tx1_state $end
$var reg 4 @ anodos_o [3:0] $end
$var reg 1 A dequeue $end
$var reg 4 B driver7seg1_anodos [3:0] $end
$var reg 16 C driver7seg1_counter [15:0] $end
$var reg 4 D driver7seg1_hundred [3:0] $end
$var reg 4 E driver7seg1_one [3:0] $end
$var reg 4 F driver7seg1_ten [3:0] $end
$var reg 4 G driver7seg1_thousand [3:0] $end
$var reg 1 H driver7seg1_tick $end
$var reg 1 I rx_ready $end
$var reg 8 J segmentos_o [7:0] $end
$var reg 1 K state $end
$var reg 1 L tx_o $end
$var reg 1 M tx_ready $end
$var reg 1 N tx_start $end
$scope begin DUT_DRIVER7SEG1_ANODOS_PROC $end
$upscope $end
$scope begin DUT_DRIVER7SEG1_BIN2BCD1_ASSIGN_PROC $end
$upscope $end
$scope begin DUT_DRIVER7SEG1_BIN2BCD1_DECOMP_PROC $end
$var integer 32 O hundred [31:0] $end
$var integer 32 P i [31:0] $end
$var integer 32 Q one [31:0] $end
$var integer 32 R ten [31:0] $end
$var integer 32 S thousand [31:0] $end
$upscope $end
$scope begin DUT_DRIVER7SEG1_CNT_ANODOS_PROC $end
$upscope $end
$scope begin DUT_DRIVER7SEG1_SEGMENTOS_PROC $end
$upscope $end
$scope begin DUT_FIFO1_ADDR_PTR_PROC $end
$upscope $end
$scope begin DUT_FIFO1_RAM_DP1_RAM_PROC $end
$upscope $end
$scope begin DUT_L_STATE_M $end
$upscope $end
$scope begin DUT_UART1_CLK_DIV1_COUNTER16_PROC $end
$upscope $end
$scope begin DUT_UART1_CLK_DIV1_COUNTER_PROC $end
$upscope $end
$scope begin DUT_UART1_CLK_DIV1_UART_TICK_PROC $end
$upscope $end
$scope begin DUT_UART1_UART_RX1_FSM_PROC $end
$upscope $end
$scope begin DUT_UART1_UART_RX1_NXT_BIT_PROC $end
$upscope $end
$scope begin DUT_UART1_UART_RX1_RX_SYNC_PROC $end
$upscope $end
$scope begin DUT_UART1_UART_RX1_START_BIT_PROC $end
$upscope $end
$scope begin DUT_UART1_UART_TX1_TX_STATE_M $end
$upscope $end
$upscope $end
$upscope $end
$enddefinitions $end
#0
$dumpvars
bx S
bx R
bx Q
bx P
bx O
xN
xM
xL
xK
bx J
xI
xH
bx G
bx F
bx E
bx D
bx C
bx B
xA
bx @
x?
bx >
bx =
bx <
bx ;
x:
bx 9
bx 8
bx 7
bx 6
x5
x4
bx 3
bx 2
bx 1
bx 0
bx /
bx .
x-
x,
bx +
bx *
x)
bx (
x'
x&
x%
x$
x#
x"
x!
$end
#2
1)
1'
0$
#1002
1#
b11 J
b1 @
0!
0&
0,
b0 +
0"
0K
0N
0A
b1 B
b0 C
0H
b0 F
b0 E
b0 G
b0 D
b0 /
1%
1-
b0 *
b0 .
b0 0
b0 (
b0 9
b0 <
b0 6
0I
b0 8
0:
b0 7
b111 ;
0L
b0 =
0M
b0 >
0?
04
05
b0 3
b0 2
1$
#2002
0$
#3002
1$
#4002
0$
#5002
1$
#6002
0$
#7002
1$
#8002
0$
#9002
1$
#10002
0'
0$
#11002
b1 C
1L
1M
14
b1 3
b1 2
b11 Q
b11 R
b11 O
b11 S
b1011 P
1$
#12002
0$
#13002
b10 C
04
b10 3
b1011 P
1$
#14002
0$
#15002
b11 C
b11 3
b1011 P
1$
#16002
0$
#17002
b100 C
b100 3
b1011 P
1$
#18002
0$
#19002
b101 C
b101 3
b1011 P
1$
#20002
0$
#21002
b110 C
b110 3
b1011 P
1$
#22002
0$
#23002
b111 C
b111 3
b1011 P
1$
#24002
0$
#25002
b1000 C
b1000 3
b1011 P
1$
#26002
0$
#27002
b1001 C
b1001 3
b1011 P
1$
#28002
0$
#29002
b1010 C
b1010 3
b1011 P
1$
#30002
0$
#31002
b1011 C
b1011 3
b1011 P
1$
#32002
0$
#33002
b1100 C
b1100 3
b1011 P
1$
#34002
0$
#35002
b1101 C
b0 3
b1011 P
1$
#36002
0$
#37002
b1110 C
14
b1 3
b10 2
b1011 P
1$
#38002
0$
#39002
b1111 C
04
b10 3
b1011 P
1$
#40002
0$
#41002
b10000 C
b11 3
b1011 P
1$
#42002
0$
#43002
b10001 C
b100 3
b1011 P
1$
#44002
0$
#45002
b10010 C
b101 3
b1011 P
1$
#46002
0$
#47002
b10011 C
b110 3
b1011 P
1$
#48002
0$
#49002
b10100 C
b111 3
b1011 P
1$
#50002
0$
#51002
b10101 C
b1000 3
b1011 P
1$
#52002
0$
#53002
b10110 C
b1001 3
b1011 P
1$
#54002
0$
#55002
b10111 C
b1010 3
b1011 P
1$
#56002
0$
#57002
b11000 C
b1011 3
b1011 P
1$
#58002
0$
#59002
b11001 C
b1100 3
b1011 P
1$
#60002
0$
#61002
b11010 C
b0 3
b1011 P
1$
#62002
0$
#63002
b11011 C
14
b1 3
b11 2
b1011 P
1$
#64002
0$
#65002
b11100 C
04
b10 3
b1011 P
1$
#66002
0$
#67002
b11101 C
b11 3
b1011 P
1$
#68002
0$
#69002
b11110 C
b100 3
b1011 P
1$
#70002
0$
#71002
b11111 C
b101 3
b1011 P
1$
#72002
0$
#73002
b100000 C
b110 3
b1011 P
1$
#74002
0$
#75002
b100001 C
b111 3
b1011 P
1$
#76002
0$
#77002
b100010 C
b1000 3
b1011 P
1$
#78002
0$
#79002
b100011 C
b1001 3
b1011 P
1$
#80002
0$
#81002
b100100 C
b1010 3
b1011 P
1$
#82002
0$
#83002
b100101 C
b1011 3
b1011 P
1$
#84002
0$
#85002
b100110 C
b1100 3
b1011 P
1$
#86002
0$
#87002
b100111 C
b0 3
b1011 P
1$
#88002
0$
#89002
b101000 C
14
b1 3
b100 2
b1011 P
1$
#90002
0$
#91002
b101001 C
04
b10 3
b1011 P
1$
#92002
0$
#93002
b101010 C
b11 3
b1011 P
1$
#94002
0$
#95002
b101011 C
b100 3
b1011 P
1$
#96002
0$
#97002
b101100 C
b101 3
b1011 P
1$
#98002
0$
#99002
b101101 C
b110 3
b1011 P
1$
#100002
0$
#101002
b101110 C
b111 3
b1011 P
1$
#102002
0$
#103002
b101111 C
b1000 3
b1011 P
1$
#104002
0$
#105002
b110000 C
b1001 3
b1011 P
1$
#106002
0$
#107002
b110001 C
b1010 3
b1011 P
1$
#108002
0$
#109002
b110010 C
b1011 3
b1011 P
1$
#110002
0$
#111002
b110011 C
b1100 3
b1011 P
1$
#112002
0$
#113002
b110100 C
b0 3
b1011 P
1$
#114002
0$
#115002
b110101 C
14
b1 3
b101 2
b1011 P
1$
#116002
0$
#117002
b110110 C
04
b10 3
b1011 P
1$
#118002
0$
#119002
b110111 C
b11 3
b1011 P
1$
#120002
0$
#121002
b111000 C
b100 3
b1011 P
1$
#122002
0$
#123002
b111001 C
b101 3
b1011 P
1$
#124002
0$
#125002
b111010 C
b110 3
b1011 P
1$
#126002
0$
#127002
b111011 C
b111 3
b1011 P
1$
#128002
0$
#129002
b111100 C
b1000 3
b1011 P
1$
#130002
0$
#131002
b111101 C
b1001 3
b1011 P
1$
#132002
0$
#133002
b111110 C
b1010 3
b1011 P
1$
#134002
0$
#135002
b111111 C
b1011 3
b1011 P
1$
#136002
0$
#137002
b1000000 C
b1100 3
b1011 P
1$
#138002
0$
#139002
b1000001 C
b0 3
b1011 P
1$
#140002
0$
#141002
b1000010 C
14
b1 3
b110 2
b1011 P
1$
#142002
0$
#143002
b1000011 C
04
b10 3
b1011 P
1$
#144002
0$
#145002
b1000100 C
b11 3
b1011 P
1$
#146002
0$
#147002
b1000101 C
b100 3
b1011 P
1$
#148002
0$
#149002
b1000110 C
b101 3
b1011 P
1$
#150002
0$
#151002
b1000111 C
b110 3
b1011 P
1$
#152002
0$
#153002
b1001000 C
b111 3
b1011 P
1$
#154002
0$
#155002
b1001001 C
b1000 3
b1011 P
1$
#156002
0$
#157002
b1001010 C
b1001 3
b1011 P
1$
#158002
0$
#159002
b1001011 C
b1010 3
b1011 P
1$
#160002
0$
#161002
b1001100 C
b1011 3
b1011 P
1$
#162002
0$
#163002
b1001101 C
b1100 3
b1011 P
1$
#164002
0$
#165002
b1001110 C
b0 3
b1011 P
1$
#166002
0$
#167002
b1001111 C
14
b1 3
b111 2
b1011 P
1$
#168002
0$
#169002
b1010000 C
04
b10 3
b1011 P
1$
#170002
0$
#171002
b1010001 C
b11 3
b1011 P
1$
#172002
0$
#173002
b1010010 C
b100 3
b1011 P
1$
#174002
0$
#175002
b1010011 C
b101 3
b1011 P
1$
#176002
0$
#177002
b1010100 C
b110 3
b1011 P
1$
#178002
0$
#179002
b1010101 C
b111 3
b1011 P
1$
#180002
0$
#181002
b1010110 C
b1000 3
b1011 P
1$
#182002
0$
#183002
b1010111 C
b1001 3
b1011 P
1$
#184002
0$
#185002
b1011000 C
b1010 3
b1011 P
1$
#186002
0$
#187002
b1011001 C
b1011 3
b1011 P
1$
#188002
0$
#189002
b1011010 C
b1100 3
b1011 P
1$
#190002
0$
#191002
b1011011 C
b0 3
b1011 P
1$
#192002
0$
#193002
b1011100 C
14
b1 3
b0 2
b1011 P
1$
#194002
0$
#195002
b1011101 C
15
04
b10 3
b1011 P
1$
#196002
0$
#197002
b1011110 C
05
b11 3
b1011 P
1$
#198002
0$
#199002
b1011111 C
b100 3
b1011 P
1$
#200002
0$
#201002
b1100000 C
b101 3
b1011 P
1$
#202002
0$
#203002
b1100001 C
b110 3
b1011 P
1$
#204002
0$
#205002
b1100010 C
b111 3
b1011 P
1$
#206002
0$
#207002
b1100011 C
b1000 3
b1011 P
1$
#208002
0$
#209002
b1100100 C
b1001 3
b1011 P
1$
#210002
0$
#211002
b1100101 C
b1010 3
b1011 P
1$
#212002
0$
#213002
b1100110 C
b1011 3
b1011 P
1$
#214002
0$
#215002
b1100111 C
b1100 3
b1011 P
1$
#216002
0$
#217002
b1101000 C
b0 3
b1011 P
1$
#218002
0$
#219002
b1101001 C
14
b1 3
b1 2
b1011 P
1$
#220002
0$
#221002
b1101010 C
04
b10 3
b1011 P
1$
#222002
0$
#223002
b1101011 C
b11 3
b1011 P
1$
#224002
0$
#225002
b1101100 C
b100 3
b1011 P
1$
#226002
0$
#227002
b1101101 C
b101 3
b1011 P
1$
#228002
0$
#229002
b1101110 C
b110 3
b1011 P
1$
#230002
0$
#231002
b1101111 C
b111 3
b1011 P
1$
#232002
0$
#233002
b1110000 C
b1000 3
b1011 P
1$
#234002
0$
#235002
b1110001 C
b1001 3
b1011 P
1$
#236002
0$
#237002
b1110010 C
b1010 3
b1011 P
1$
#238002
0$
#239002
b1110011 C
b1011 3
b1011 P
1$
#240002
0$
#241002
b1110100 C
b1100 3
b1011 P
1$
#242002
0$
#243002
b1110101 C
b0 3
b1011 P
1$
#244002
0$
#245002
b1110110 C
14
b1 3
b10 2
b1011 P
1$
#246002
0$
#247002
b1110111 C
04
b10 3
b1011 P
1$
#248002
0$
#249002
b1111000 C
b11 3
b1011 P
1$
#250002
0$
#251002
b1111001 C
b100 3
b1011 P
1$
#252002
0$
#253002
b1111010 C
b101 3
b1011 P
1$
#254002
0$
#255002
b1111011 C
b110 3
b1011 P
1$
#256002
0$
#257002
b1111100 C
b111 3
b1011 P
1$
#258002
0$
#259002
b1111101 C
b1000 3
b1011 P
1$
#260002
0$
#261002
b1111110 C
b1001 3
b1011 P
1$
#262002
0$
#263002
b1111111 C
b1010 3
b1011 P
1$
#264002
0$
#265002
b10000000 C
b1011 3
b1011 P
1$
#266002
0$
#267002
b10000001 C
b1100 3
b1011 P
1$
#268002
0$
#269002
b10000010 C
b0 3
b1011 P
1$
#270002
0$
#271002
b10000011 C
14
b1 3
b11 2
b1011 P
1$
#272002
0$
#273002
b10000100 C
04
b10 3
b1011 P
1$
#274002
0$
#275002
b10000101 C
b11 3
b1011 P
1$
#276002
0$
#277002
b10000110 C
b100 3
b1011 P
1$
#278002
0$
#279002
b10000111 C
b101 3
b1011 P
1$
#280002
0$
#281002
b10001000 C
b110 3
b1011 P
1$
#282002
0$
#283002
b10001001 C
b111 3
b1011 P
1$
#284002
0$
#285002
b10001010 C
b1000 3
b1011 P
1$
#286002
0$
#287002
b10001011 C
b1001 3
b1011 P
1$
#288002
0$
#289002
b10001100 C
b1010 3
b1011 P
1$
#290002
0$
#291002
b10001101 C
b1011 3
b1011 P
1$
#292002
0$
#293002
b10001110 C
b1100 3
b1011 P
1$
#294002
0$
#295002
b10001111 C
b0 3
b1011 P
1$
#296002
0$
#297002
b10010000 C
14
b1 3
b100 2
b1011 P
1$
#298002
0$
#299002
b10010001 C
04
b10 3
b1011 P
1$
#300002
0$
#301002
b10010010 C
b11 3
b1011 P
1$
#302002
0$
#303002
b10010011 C
b100 3
b1011 P
1$
#304002
0$
#305002
b10010100 C
b101 3
b1011 P
1$
#306002
0$
#307002
b10010101 C
b110 3
b1011 P
1$
#308002
0$
#309002
b10010110 C
b111 3
b1011 P
1$
#310002
0$
#311002
b10010111 C
b1000 3
b1011 P
1$
